{
  "Name": "xaz",
  "Description": "Creates a new record of type xaz",
  "HttpMethod": "POST",
  "IsEnabled": true,
  "OrderIndex": 1035,
  "CrossDomainPolicy": "PortalAliasesOnly",
  "Inputs": [
    {
      "Name": "name",
      "IsDeleted": false,
      "IsEnabled": true,
      "OrderIndex": 0,
      "Parameters": {},
      "InputTypeStr": "text",
      "Validations": [
        {
          "Data": "{\"Message\":\"name is required.\"}",
          "Type": "default-required",
          "IsDeleted": false,
          "IsEnabled": false,
          "OrderIndex": 0
        }
      ]
    },
    {
      "Name": "docs",
      "IsDeleted": false,
      "IsEnabled": true,
      "OrderIndex": 1,
      "Parameters": {},
      "InputTypeStr": "text",
      "Validations": []
    }
  ],
  "Actions": [
    {
      "ActionType": "PlantAnApp.CreateEntity.0.xaz",
      "OrderIndex": 0,
      "Parameters": {
        "OutputToken": "CreatedRecordId",
        "name": "[name]",
        "docs": "[docs]"
      },
      "IsEnabled": true,
      "ExecutionType": "OnExecute",
      "Metadata": {
        "PAP_InternalIdentifier": "Api.CreateEntity",
        "EntityName": "xaz"
      }
    },
    {
      "ActionType": "PlantAnApp.ReadEntity.0.xaz",
      "OrderIndex": 1,
      "Parameters": {
        "RecordId": "[CreatedRecordId]",
        "OutputToken": "CreatedRecord"
      },
      "IsEnabled": true,
      "ExecutionType": "OnExecute",
      "Metadata": {
        "PAP_InternalIdentifier": "Api.ReadEntity",
        "EntityName": "xaz"
      }
    },
    {
      "ActionType": "JsonObject",
      "OrderIndex": 2,
      "Parameters": {
        "HttpCode": "201 Created",
        "Fields": [
          {
            "name": "Id",
            "value": "[CreatedRecordId]"
          },
          {
            "name": "name",
            "value": "[CreatedRecord:name]"
          },
          {
            "name": "docs",
            "value": "[CreatedRecord:docs]"
          }
        ],
        "Headers": [
          {
            "name": "Location",
            "value": "http://localhost:8931/api/xaz?recordId=[CreatedRecordId]"
          }
        ]
      },
      "IsEnabled": true,
      "ExecutionType": "OnExecute",
      "Metadata": {
        "PAP_InternalIdentifier": "Api.Response"
      }
    }
  ],
  "OnErrorActions": []
}